dsb/network.py
dsb/parser.py
dsb/dsb.py
dsb/exceptions.py
dsb/__init__.py
DSBPy-0.1.0.dist-info/RECORD
DSBPy-0.1.0.dist-info/METADATA
DSBPy-0.1.0.dist-info/DESCRIPTION.rst
DSBPy-0.1.0.dist-info/top_level.txt
DSBPy-0.1.0.dist-info/WHEEL
DSBPy-0.1.0.dist-info/metadata.json
