Metadata-Version: 2.0
Name: DSBPy
Version: 0.1.0
Summary: A Python-Interface for DSB
Home-page: https://github.com/Thor77/DSBPy
Author: Thor77
Author-email: thor77@thor77.org
License: UNKNOWN
Keywords: dsbpy dsb dasschwarzebrett school
Platform: UNKNOWN
Requires-Dist: requests
Requires-Dist: beautifulsoup4
